COPYING
MANIFEST.in
README
health_ophtalmo_view.xml
setup.cfg
setup.py
./__init__.py
./__tryton__.py
./health_ophtalmo.py
./tests/__init__.py
./tests/test_health_ophtalmo.py
locale/el.po
locale/es_ES.po
locale/fa.po
locale/fr_FR.po
locale/it.po
security/access_rights.xml
trytond_health_ophtalmo.egg-info/PKG-INFO
trytond_health_ophtalmo.egg-info/SOURCES.txt
trytond_health_ophtalmo.egg-info/dependency_links.txt
trytond_health_ophtalmo.egg-info/entry_points.txt
trytond_health_ophtalmo.egg-info/not-zip-safe
trytond_health_ophtalmo.egg-info/requires.txt
trytond_health_ophtalmo.egg-info/top_level.txt