Metadata-Version: 1.1
Name: trytond-health-ophtalmo
Version: 1.0.0
Summary: 
